root_krd/__init__.py
root_krd/root_krd.py
root_krd-1.0.0.dist-info/METADATA
root_krd-1.0.0.dist-info/WHEEL
root_krd-1.0.0.dist-info/top_level.txt
root_krd-1.0.0.dist-info/RECORD
