Metadata-Version: 2.1
Name: root-krd
Version: 1.0.0
Requires-Dist: requests
